pyeda31/__init__.py
pyeda31/check_csv.py
pyeda31/data_summary.py
pyeda31/pymissing_values_summary.py
pyeda31-1.5.2.dist-info/LICENSE
pyeda31-1.5.2.dist-info/METADATA
pyeda31-1.5.2.dist-info/WHEEL
pyeda31-1.5.2.dist-info/RECORD
