Metadata-Version: 2.3
Name: pyeda31
Version: 1.5.2
Summary: A python package to support exploratory data analysis!
License: MIT
Author: Catherine Meng, Jessie Zhang, Zheng He
Requires-Python: >=3.10,<4.0
Classifier: License :: OSI Approved :: MIT License
Classifier: Programming Language :: Python :: 3
Classifier: Programming Language :: Python :: 3.10
Classifier: Programming Language :: Python :: 3.11
Classifier: Programming Language :: Python :: 3.12
Classifier: Programming Language :: Python :: 3.13
Requires-Dist: pandas (>=2.2.3,<3.0.0)
